{
  "_class": "text",
  "attributedString": {
    "_class": "attributedString",
    "attributes": [
      {
        "_class": "stringAttribute",
        "attributes": {
          "MSAttributedStringColorAttribute": {
            "_class": "color",
            "alpha": 1,
            "blue": 0.2,
            "green": 0.2,
            "red": 0.2
          },
          "MSAttributedStringFontAttribute": {
            "_class": "fontDescriptor",
            "attributes": {
              "name": "TsukuARdGothic-Bold",
              "size": 23.95798633796646
            }
          },
          "MSAttributedStringTextTransformAttribute": 0,
          "kerning": 0.59925,
          "paragraphStyle": {
            "_class": "paragraphStyle",
            "alignment": 2,
            "maximumLineHeight": 36.98145575739504,
            "minimumLineHeight": 36.98145575739504,
            "paragraphSpacing": 1
          },
          "strikethroughStyle": 0,
          "underlineStyle": 0
        },
        "length": 1,
        "location": 0
      },
      {
        "_class": "stringAttribute",
        "attributes": {
          "MSAttributedStringColorAttribute": {
            "_class": "color",
            "alpha": 1,
            "blue": 0.2,
            "green": 0.2,
            "red": 0.2
          },
          "MSAttributedStringFontAttribute": {
            "_class": "fontDescriptor",
            "attributes": {
              "name": "TsukuARdGothic-Bold",
              "size": 27.95787060772218
            }
          },
          "MSAttributedStringTextTransformAttribute": 0,
          "kerning": 0.69929725,
          "paragraphStyle": {
            "_class": "paragraphStyle",
            "alignment": 2,
            "maximumLineHeight": 36.98145575739504,
            "minimumLineHeight": 36.98145575739504,
            "paragraphSpacing": 1
          },
          "strikethroughStyle": 0,
          "underlineStyle": 0
        },
        "length": 4,
        "location": 1
      }
    ],
    "string": "の有料会員"
  },
  "automaticallyDrawOnUnderlyingPath": false,
  "do_objectID": "4B636FE2-13AB-49A1-9BA7-38C8332755B7",
  "dontSynchroniseWithSymbol": false,
  "exportOptions": {
    "_class": "exportOptions",
    "do_objectID": "C96823F8-0C21-4067-9AC3-573DFA86CD62",
    "exportFormats": [
    ],
    "includedLayerIds": [
    ],
    "layerOptions": 0,
    "shouldTrim": false
  },
  "frame": {
    "_class": "rect",
    "constrainProportions": false,
    "do_objectID": "164DC6DF-CA37-4BE2-B55A-3F1727FC93F7",
    "height": 37,
    "width": 164,
    "x": 547,
    "y": 8.485945000000001
  },
  "glyphBounds": "{{0, 0}, {0, 0}}",
  "isFlippedHorizontal": false,
  "isFlippedVertical": false,
  "isLocked": false,
  "isVisible": true,
  "layerListExpandedType": 0,
  "lineSpacingBehaviour": 2,
  "name": "の有料会員",
  "nameIsFixed": false,
  "resizingConstraint": 63,
  "resizingType": 0,
  "rotation": 0,
  "shouldBreakMaskChain": false,
  "style": {
    "_class": "style",
    "do_objectID": "B7E98513-51D3-4D08-BC79-D60353800E68",
    "endDecorationType": 0,
    "miterLimit": 10,
    "startDecorationType": 0
  },
  "textBehaviour": 1,
  "userInfo": {
    "com.animaapp.stc-sketch-plugin": {
      "kModelPropertiesKey": {
        "isAutoWidth": 0
      }
    }
  }
}