{
  "_class": "shapeGroup",
  "clippingMaskMode": 0,
  "do_objectID": "5D5EE121-5CEF-4B00-B35C-274D01E0DE39",
  "exportOptions": {
    "_class": "exportOptions",
    "do_objectID": "70976E1E-52F4-4C63-8DF5-455D2B276E08",
    "exportFormats": [
    ],
    "includedLayerIds": [
    ],
    "layerOptions": 0,
    "shouldTrim": false
  },
  "frame": {
    "_class": "rect",
    "constrainProportions": false,
    "do_objectID": "92D69EBB-FBFB-46D1-AFA6-801279455FA8",
    "height": 3,
    "width": 50,
    "x": 54,
    "y": 39
  },
  "hasClickThrough": false,
  "hasClippingMask": false,
  "isFlippedHorizontal": false,
  "isFlippedVertical": false,
  "isLocked": false,
  "isVisible": true,
  "layerListExpandedType": 0,
  "layers": [
    {
      "class": "rectangle",
      "id": "9A3472DC-9509-437A-82C8-F6DF53B49D0C"
    }
  ],
  "name": "Rectangle 5",
  "nameIsFixed": false,
  "resizingConstraint": 63,
  "resizingType": 0,
  "rotation": 0,
  "shouldBreakMaskChain": false,
  "style": {
    "_class": "style",
    "borders": [
      {
        "_class": "border",
        "color": {
          "_class": "color",
          "alpha": 1,
          "blue": 0.592,
          "green": 0.592,
          "red": 0.592
        },
        "fillType": 0,
        "isEnabled": false,
        "position": 1,
        "thickness": 1
      }
    ],
    "do_objectID": "C2B849B7-5B74-4F08-9C49-06B5C18ADEB2",
    "endDecorationType": 0,
    "fills": [
      {
        "_class": "fill",
        "color": {
          "_class": "color",
          "alpha": 1,
          "blue": 0.0235294117647059,
          "green": 0.6078431372549019,
          "red": 0.2156862745098039
        },
        "fillType": 0,
        "isEnabled": true,
        "noiseIndex": 0,
        "noiseIntensity": 0,
        "patternFillType": 1,
        "patternTileScale": 1
      }
    ],
    "miterLimit": 10,
    "shadows": [
      {
        "_class": "shadow",
        "blurRadius": 0,
        "color": {
          "_class": "color",
          "alpha": 1,
          "blue": 0.0235294117647059,
          "green": 0.6078431372549019,
          "red": 0.215686274509804
        },
        "contextSettings": {
          "_class": "graphicsContextSettings",
          "blendMode": 0,
          "opacity": 1
        },
        "isEnabled": false,
        "offsetX": 0,
        "offsetY": -1,
        "spread": 0
      }
    ],
    "sharedObjectID": "005C43DF-888C-41C7-B10E-F952CEE17BA4",
    "startDecorationType": 0
  },
  "userInfo": {
    "com.animaapp.stc-sketch-plugin": {
      "kModelPropertiesKey": {
      }
    }
  },
  "windingRule": 1
}