{
  "_class": "text",
  "attributedString": {
    "_class": "attributedString",
    "attributes": [
      {
        "_class": "stringAttribute",
        "attributes": {
          "MSAttributedStringColorAttribute": {
            "_class": "color",
            "alpha": 1,
            "blue": 0.082353,
            "green": 0.094118,
            "red": 0.121569
          },
          "MSAttributedStringFontAttribute": {
            "_class": "fontDescriptor",
            "attributes": {
              "name": "KozGoPr6N-Regular",
              "size": 23.95337881572645
            }
          },
          "MSAttributedStringTextTransformAttribute": 0,
          "kerning": 2.8747008,
          "paragraphStyle": {
            "_class": "paragraphStyle",
            "alignment": 0,
            "maximumLineHeight": 29.99691784849931,
            "minimumLineHeight": 29.99691784849931,
            "paragraphSpacing": 1
          },
          "strikethroughStyle": 0,
          "underlineStyle": 0
        },
        "length": 32,
        "location": 0
      }
    ],
    "string": "最適化されたバッファー組成により、特異性の高いPCRが可能。  "
  },
  "automaticallyDrawOnUnderlyingPath": false,
  "do_objectID": "3B9B5218-6CB2-4BC1-9AB0-D32937F45D4C",
  "dontSynchroniseWithSymbol": false,
  "exportOptions": {
    "_class": "exportOptions",
    "do_objectID": "FE83E974-A9DB-4E17-95D7-D014AB3876D6",
    "exportFormats": [
    ],
    "includedLayerIds": [
    ],
    "layerOptions": 0,
    "shouldTrim": false
  },
  "frame": {
    "_class": "rect",
    "constrainProportions": false,
    "do_objectID": "72D86039-5543-4E05-AA4E-5CC4860A65EF",
    "height": 30,
    "width": 786,
    "x": 53,
    "y": 4.977919999999999
  },
  "glyphBounds": "{{0, 0}, {0, 0}}",
  "isFlippedHorizontal": false,
  "isFlippedVertical": false,
  "isLocked": false,
  "isVisible": true,
  "layerListExpandedType": 0,
  "lineSpacingBehaviour": 2,
  "name": "最適化されたバッファー組成により、特異性の高いPCRが可能。  ",
  "nameIsFixed": false,
  "resizingConstraint": 63,
  "resizingType": 0,
  "rotation": 0,
  "shouldBreakMaskChain": false,
  "style": {
    "_class": "style",
    "do_objectID": "46F15D69-2D26-4F2E-8E68-E8BA387B97A9",
    "endDecorationType": 0,
    "miterLimit": 10,
    "startDecorationType": 0
  },
  "textBehaviour": 1,
  "userInfo": {
    "com.animaapp.stc-sketch-plugin": {
      "kModelPropertiesKey": {
        "isAutoWidth": 0
      }
    }
  }
}