{
  "_class": "group",
  "do_objectID": "FB60B28E-2AF1-483F-A0C1-96C894A7A0A2",
  "exportOptions": {
    "_class": "exportOptions",
    "do_objectID": "00F02D3B-E810-42A1-85F0-1362B14209A8",
    "exportFormats": [
    ],
    "includedLayerIds": [
    ],
    "layerOptions": 0,
    "shouldTrim": false
  },
  "frame": {
    "_class": "rect",
    "constrainProportions": false,
    "do_objectID": "C10B4553-703A-46C1-BA47-33E6EED9526E",
    "height": 280,
    "width": 230,
    "x": 210,
    "y": -1642
  },
  "hasClickThrough": false,
  "isFlippedHorizontal": false,
  "isFlippedVertical": false,
  "isLocked": false,
  "isVisible": true,
  "layerListExpandedType": 0,
  "layers": [
    {
      "class": "group",
      "id": "A2635B76-1603-41CA-BA22-7FD52A3C590E"
    },
    {
      "class": "shapeGroup",
      "id": "B2BE1F58-A3A5-4035-B815-2E59A7562A9C"
    },
    {
      "class": "shapeGroup",
      "id": "30F524FF-98E4-41ED-AE06-5BE30F7EB006"
    },
    {
      "class": "shapeGroup",
      "id": "4305FD2E-ED9A-4852-9026-D373741449F6"
    },
    {
      "class": "text",
      "id": "6F9FAB4A-C1F8-4EF1-A242-EB11557AF1A1"
    },
    {
      "class": "text",
      "id": "AEDD1C98-1D38-4B65-B2F6-EC17C39F49F7"
    },
    {
      "class": "text",
      "id": "87BFEA58-54EF-4526-8954-940C62D0ACFC"
    },
    {
      "class": "text",
      "id": "79E55D5F-85C0-4033-86F1-7F3140D66709"
    },
    {
      "class": "text",
      "id": "934EBDFF-F7F4-4638-B5F1-74FC1B06D762"
    },
    {
      "class": "text",
      "id": "E94A217B-ED85-4EFC-B453-E29CA99F52C0"
    },
    {
      "class": "text",
      "id": "4806DA94-7069-4875-B325-10C833DB5762"
    },
    {
      "class": "text",
      "id": "3768B666-321B-4782-9FC1-8CBC8C841221"
    },
    {
      "class": "text",
      "id": "E8CC8F63-A95C-4327-A9CE-CF1B3C8E4789"
    }
  ],
  "name": "Group 7",
  "nameIsFixed": false,
  "resizingConstraint": 63,
  "resizingType": 0,
  "rotation": 0,
  "shouldBreakMaskChain": false,
  "style": {
    "_class": "style",
    "do_objectID": "521B21E8-5575-46B8-9A67-70BA8F08A553",
    "endDecorationType": 0,
    "miterLimit": 10,
    "startDecorationType": 0
  },
  "userInfo": {
    "com.animaapp.stc-sketch-plugin": {
      "kModelPropertiesKey": {
      }
    }
  }
}