{
  "_class": "text",
  "attributedString": {
    "_class": "attributedString",
    "attributes": [
      {
        "_class": "stringAttribute",
        "attributes": {
          "MSAttributedStringColorAttribute": {
            "_class": "color",
            "alpha": 1,
            "blue": 0.3529411765,
            "green": 0.337254902,
            "red": 0.3333333333
          },
          "MSAttributedStringFontAttribute": {
            "_class": "fontDescriptor",
            "attributes": {
              "name": "YuGo-Bold",
              "size": 15
            }
          },
          "kerning": 0,
          "paragraphStyle": {
            "_class": "paragraphStyle",
            "alignment": 0,
            "allowsDefaultTighteningForTruncation": 0
          }
        },
        "length": 9,
        "location": 0
      }
    ],
    "string": "会社名 / 組織名"
  },
  "automaticallyDrawOnUnderlyingPath": false,
  "do_objectID": "B048182E-5C9A-4B9E-AFDE-BF5F4B67C3E5",
  "dontSynchroniseWithSymbol": false,
  "exportOptions": {
    "_class": "exportOptions",
    "do_objectID": "DCE83B4C-1500-404D-8E51-E57EA6462EF4",
    "exportFormats": [
    ],
    "includedLayerIds": [
    ],
    "layerOptions": 0,
    "shouldTrim": false
  },
  "frame": {
    "_class": "rect",
    "constrainProportions": false,
    "do_objectID": "7F9C5040-440F-4C04-B50A-4CDD2E6BC8FA",
    "height": 15,
    "width": 107,
    "x": 0,
    "y": 0
  },
  "glyphBounds": "{{0, 0}, {105, 15}}",
  "isFlippedHorizontal": false,
  "isFlippedVertical": false,
  "isLocked": false,
  "isVisible": true,
  "layerListExpandedType": 0,
  "lineSpacingBehaviour": 2,
  "name": "メールアドレス",
  "nameIsFixed": false,
  "resizingConstraint": 47,
  "resizingType": 0,
  "rotation": 0,
  "shouldBreakMaskChain": false,
  "style": {
    "_class": "style",
    "do_objectID": "1576670E-61A1-4D17-A08E-8F42EE87A4F3",
    "endDecorationType": 0,
    "miterLimit": 10,
    "startDecorationType": 0,
    "textStyle": {
      "_class": "textStyle",
      "do_objectID": "D8C98FA9-0EE2-4434-91A8-E801CD35F392",
      "encodedAttributes": {
        "MSAttributedStringColorAttribute": {
          "_class": "color",
          "alpha": 1,
          "blue": 0.3529411765,
          "green": 0.337254902,
          "red": 0.3333333333
        },
        "MSAttributedStringFontAttribute": {
          "_class": "fontDescriptor",
          "attributes": {
            "name": "YuGo-Bold",
            "size": 15
          }
        },
        "kerning": 0,
        "paragraphStyle": {
          "_class": "paragraphStyle",
          "alignment": 0,
          "allowsDefaultTighteningForTruncation": 0
        }
      },
      "verticalAlignment": 0
    }
  },
  "textBehaviour": 0,
  "userInfo": {
    "com.animaapp.stc-sketch-plugin": {
      "kModelPropertiesKey": {
        "isAutoWidth": 1
      }
    }
  }
}