{
  "_class": "shapeGroup",
  "clippingMaskMode": 0,
  "do_objectID": "02CD042D-0E55-4A66-A2C9-FDDA46830FD5",
  "exportOptions": {
    "_class": "exportOptions",
    "do_objectID": "5F930776-EC3D-48D5-9A44-FD70CE627FA2",
    "exportFormats": [
    ],
    "includedLayerIds": [
    ],
    "layerOptions": 0,
    "shouldTrim": false
  },
  "frame": {
    "_class": "rect",
    "constrainProportions": false,
    "do_objectID": "9E035CA8-5D60-46D1-AE81-D9B6471F8BA0",
    "height": 15,
    "width": 15,
    "x": 0,
    "y": 301
  },
  "hasClickThrough": false,
  "hasClippingMask": true,
  "isFlippedHorizontal": false,
  "isFlippedVertical": false,
  "isLocked": false,
  "isVisible": true,
  "layerListExpandedType": 2,
  "layers": [
    {
      "class": "rectangle",
      "id": "329A9CC4-CE22-4A8C-A5D7-42F00F4029E6"
    }
  ],
  "name": "虫眼鏡のアイコン",
  "nameIsFixed": false,
  "resizingConstraint": 63,
  "resizingType": 0,
  "rotation": 0,
  "shouldBreakMaskChain": false,
  "style": {
    "_class": "style",
    "do_objectID": "24A7625A-9576-48E8-9030-267920B1891F",
    "endDecorationType": 0,
    "fills": [
      {
        "_class": "fill",
        "color": {
          "_class": "color",
          "alpha": 1,
          "blue": 0,
          "green": 0,
          "red": 0
        },
        "fillType": 4,
        "image": {
          "_class": "MSJSONFileReference",
          "_ref": "images/7cc920d520b5dcf3f1549226491820a7c456c9e7.png",
          "_ref_class": "MSImageData"
        },
        "isEnabled": true,
        "noiseIndex": 0,
        "noiseIntensity": 0,
        "patternFillType": 1,
        "patternTileScale": 1
      }
    ],
    "miterLimit": 10,
    "startDecorationType": 0
  },
  "windingRule": 1
}