{
  "_class": "shapeGroup",
  "clippingMaskMode": 0,
  "do_objectID": "E865DB9A-2B60-4008-A6CB-656E78E50445",
  "exportOptions": {
    "_class": "exportOptions",
    "exportFormats": [
    ],
    "includedLayerIds": [
    ],
    "layerOptions": 0,
    "shouldTrim": false
  },
  "frame": {
    "_class": "rect",
    "constrainProportions": true,
    "height": 25,
    "width": 25,
    "x": 0,
    "y": 0
  },
  "hasClickThrough": false,
  "hasClippingMask": false,
  "isFlippedHorizontal": false,
  "isFlippedVertical": false,
  "isLocked": false,
  "isVisible": true,
  "layerListExpandedType": 0,
  "layers": [
    {
      "class": "rectangle",
      "id": "3BD3D3D0-5968-41E5-BB60-902F66F63695"
    }
  ],
  "name": "Rectangle 2",
  "nameIsFixed": false,
  "resizingConstraint": 63,
  "resizingType": 0,
  "rotation": 0,
  "shouldBreakMaskChain": false,
  "style": {
    "_class": "style",
    "borders": [
      {
        "_class": "border",
        "color": {
          "_class": "color",
          "alpha": 1,
          "blue": 0.592,
          "green": 0.592,
          "red": 0.592
        },
        "fillType": 0,
        "isEnabled": false,
        "position": 1,
        "thickness": 1
      }
    ],
    "endDecorationType": 0,
    "fills": [
      {
        "_class": "fill",
        "color": {
          "_class": "color",
          "alpha": 1,
          "blue": 0.9176470588235294,
          "green": 0.9176470588235294,
          "red": 0.9176470588235294
        },
        "fillType": 0,
        "isEnabled": true,
        "noiseIndex": 0,
        "noiseIntensity": 0,
        "patternFillType": 1,
        "patternTileScale": 1
      }
    ],
    "miterLimit": 10,
    "startDecorationType": 0
  },
  "userInfo": {
    "com.animaapp.stc-sketch-plugin": {
      "kModelPropertiesKey": {
        "constraints": {
          "aspectRatio": {
            "constant": 25,
            "enabled": 1,
            "modelID": "constraint_ca902aa3-42a1-43c0-a2fb-ab9178af53a5",
            "model_class": "ADModelConstraint",
            "model_version": 0.1,
            "multiplier": 25
          },
          "automatic": 1,
          "modelID": "viewConstraints_c9885acf-658e-4da6-9233-e6e2f764c761",
          "model_class": "ADModelViewConstraints",
          "model_version": 0.1,
          "scaleFactor": 1
        }
      }
    }
  },
  "windingRule": 1
}