{
  "_class": "text",
  "attributedString": {
    "_class": "attributedString",
    "attributes": [
      {
        "_class": "stringAttribute",
        "attributes": {
          "MSAttributedStringColorAttribute": {
            "_class": "color",
            "alpha": 1,
            "blue": 0.337254902,
            "green": 0.337254902,
            "red": 0.337254902
          },
          "MSAttributedStringFontAttribute": {
            "_class": "fontDescriptor",
            "attributes": {
              "name": "YuGo-Bold",
              "size": 18
            }
          },
          "paragraphStyle": {
            "_class": "paragraphStyle",
            "alignment": 0,
            "allowsDefaultTighteningForTruncation": 0,
            "maximumLineHeight": 18,
            "minimumLineHeight": 18
          }
        },
        "length": 36,
        "location": 0
      }
    ],
    "string": "これまであった新入社員研修「ワクワク冒険島」とはどのように違うのですか？"
  },
  "automaticallyDrawOnUnderlyingPath": false,
  "do_objectID": "2B477687-A3CC-4CA4-81EF-D007956C740F",
  "dontSynchroniseWithSymbol": false,
  "exportOptions": {
    "_class": "exportOptions",
    "do_objectID": "8D153B1C-8D7E-419F-971B-2607EF866672",
    "exportFormats": [
    ],
    "includedLayerIds": [
    ],
    "layerOptions": 0,
    "shouldTrim": false
  },
  "frame": {
    "_class": "rect",
    "constrainProportions": false,
    "do_objectID": "53FBC37E-7A1E-4179-9102-D62567C5EE1C",
    "height": 18,
    "width": 648,
    "x": 60,
    "y": 9
  },
  "glyphBounds": "{{3, 2}, {640, 18}}",
  "isFlippedHorizontal": false,
  "isFlippedVertical": false,
  "isLocked": false,
  "isVisible": true,
  "layerListExpandedType": 0,
  "lineSpacingBehaviour": 2,
  "name": "これまであった新入社員研修「ワクワク冒険",
  "nameIsFixed": false,
  "resizingConstraint": 47,
  "resizingType": 0,
  "rotation": 0,
  "shouldBreakMaskChain": false,
  "style": {
    "_class": "style",
    "do_objectID": "368E5255-82A6-41ED-9A05-639D9D92ACB2",
    "endDecorationType": 0,
    "miterLimit": 10,
    "sharedObjectID": "003A0B30-AE56-4B53-BC43-BE29460C6E43",
    "startDecorationType": 0,
    "textStyle": {
      "_class": "textStyle",
      "do_objectID": "0F2738A2-BD29-41A9-A55F-C922E6B08917",
      "encodedAttributes": {
        "MSAttributedStringColorAttribute": {
          "_class": "color",
          "alpha": 1,
          "blue": 0.337254902,
          "green": 0.337254902,
          "red": 0.337254902
        },
        "MSAttributedStringFontAttribute": {
          "_class": "fontDescriptor",
          "attributes": {
            "name": "YuGo-Bold",
            "size": 18
          }
        },
        "paragraphStyle": {
          "_class": "paragraphStyle",
          "alignment": 0,
          "allowsDefaultTighteningForTruncation": 0,
          "maximumLineHeight": 18,
          "minimumLineHeight": 18
        }
      },
      "verticalAlignment": 0
    }
  },
  "textBehaviour": 0,
  "userInfo": {
    "com.animaapp.stc-sketch-plugin": {
      "kModelPropertiesKey": {
        "isAutoWidth": 1
      }
    }
  }
}