{
  "_class": "text",
  "attributedString": {
    "_class": "attributedString",
    "attributes": [
      {
        "_class": "stringAttribute",
        "attributes": {
          "MSAttributedStringColorAttribute": {
            "_class": "color",
            "alpha": 1,
            "blue": 0.2,
            "green": 0.2,
            "red": 0.2
          },
          "MSAttributedStringFontAttribute": {
            "_class": "fontDescriptor",
            "attributes": {
              "name": "KozGoPr6N-Regular",
              "size": 13.99716156889821
            }
          },
          "MSAttributedStringTextTransformAttribute": 0,
          "kerning": 0.35,
          "paragraphStyle": {
            "_class": "paragraphStyle",
            "alignment": 2,
            "maximumLineHeight": 9.997972549213005,
            "minimumLineHeight": 9.997972549213005,
            "paragraphSpacing": 1
          },
          "strikethroughStyle": 0,
          "underlineStyle": 0
        },
        "length": 20,
        "location": 0
      }
    ],
    "string": "Android4.0以上で利用可能です。"
  },
  "automaticallyDrawOnUnderlyingPath": false,
  "do_objectID": "23D5236B-605A-4A19-9EA5-48EAA197E92C",
  "dontSynchroniseWithSymbol": false,
  "exportOptions": {
    "_class": "exportOptions",
    "do_objectID": "834CCE44-3F2E-466C-AEDB-E71F419C3A7A",
    "exportFormats": [
    ],
    "includedLayerIds": [
    ],
    "layerOptions": 0,
    "shouldTrim": false
  },
  "frame": {
    "_class": "rect",
    "constrainProportions": false,
    "do_objectID": "B2517CDC-93BC-4FB7-A646-F43F5FFB9657",
    "height": 14,
    "width": 237,
    "x": 11,
    "y": 264
  },
  "glyphBounds": "{{0, 0}, {0, 0}}",
  "isFlippedHorizontal": false,
  "isFlippedVertical": false,
  "isLocked": false,
  "isVisible": true,
  "layerListExpandedType": 0,
  "lineSpacingBehaviour": 2,
  "name": "Android4.0以上で利用可能です。",
  "nameIsFixed": false,
  "resizingConstraint": 63,
  "resizingType": 0,
  "rotation": 0,
  "shouldBreakMaskChain": false,
  "style": {
    "_class": "style",
    "do_objectID": "01B68CC5-1681-4621-94F0-00F0719C093E",
    "endDecorationType": 0,
    "miterLimit": 10,
    "startDecorationType": 0
  },
  "textBehaviour": 1
}