{
  "_class": "group",
  "do_objectID": "A9D9F431-ABD6-4C55-80F9-B752885AE4BC",
  "exportOptions": {
    "_class": "exportOptions",
    "do_objectID": "D5D1C9DA-9D9B-4AB5-B9B1-6C7A723FC748",
    "exportFormats": [
    ],
    "includedLayerIds": [
    ],
    "layerOptions": 0,
    "shouldTrim": false
  },
  "frame": {
    "_class": "rect",
    "constrainProportions": false,
    "do_objectID": "2F500600-34AB-41AC-B294-A4FA38381AE9",
    "height": 14,
    "width": 62,
    "x": 455,
    "y": 0
  },
  "hasClickThrough": true,
  "isFlippedHorizontal": false,
  "isFlippedVertical": false,
  "isLocked": false,
  "isVisible": true,
  "layerListExpandedType": 2,
  "layers": [
    {
      "class": "shapeGroup",
      "id": "C29BFCA9-9A40-44C4-8702-141E3E6012D5"
    }
  ],
  "name": "ほしマーク",
  "nameIsFixed": false,
  "resizingConstraint": 63,
  "resizingType": 0,
  "rotation": 0,
  "shouldBreakMaskChain": false,
  "style": {
    "_class": "style",
    "do_objectID": "831DB323-382F-4935-9BDC-FD65D207325C",
    "endDecorationType": 0,
    "fills": [
      {
        "_class": "fill",
        "color": {
          "_class": "color",
          "alpha": 0,
          "blue": 0,
          "green": 0,
          "red": 0
        },
        "fillType": 0,
        "isEnabled": true,
        "noiseIndex": 0,
        "noiseIntensity": 0,
        "patternFillType": 1,
        "patternTileScale": 1
      }
    ],
    "miterLimit": 10,
    "startDecorationType": 0
  },
  "userInfo": {
    "com.animaapp.stc-sketch-plugin": {
      "kModelPropertiesKey": {
      }
    }
  }
}